buddha/__init__.py
buddha/buddha.py
buddha-1.0.0.dist-info/DESCRIPTION.rst
buddha-1.0.0.dist-info/METADATA
buddha-1.0.0.dist-info/RECORD
buddha-1.0.0.dist-info/WHEEL
buddha-1.0.0.dist-info/entry_points.txt
buddha-1.0.0.dist-info/metadata.json
buddha-1.0.0.dist-info/top_level.txt
