Metadata-Version: 2.0
Name: buddha
Version: 1.0.0
Summary: Draw a buddha to bless your server!!!
Home-page: https://git@github.com:lucky917/buddha.git
Author: lucky917
Author-email: lucky917@foxmail.com
License: MIT
Keywords: buddha
Platform: UNKNOWN
Classifier: Development Status :: 5 - Production/Stable
Classifier: Intended Audience :: Developers
Classifier: Topic :: Software Development :: Build Tools
Classifier: License :: OSI Approved :: MIT License
Classifier: Programming Language :: Python :: 2.7
Provides-Extra: dev
Requires-Dist: check-manifest; extra == 'dev'
Provides-Extra: test
Requires-Dist: coverage; extra == 'test'
